Pop_Con-1.0.5.data/scripts/Pop-Con
Pop_Con-1.0.5.data/scripts/SFS_genotypes_profiles_plot.R
Pop_Con-1.0.5.data/scripts/plot_SFS_genotype_profiles.py
popcon/SFS_profiles_plot.py
popcon/__init__.py
popcon/heterozygosity.py
popcon/util.py
Pop_Con-1.0.5.dist-info/METADATA
Pop_Con-1.0.5.dist-info/WHEEL
Pop_Con-1.0.5.dist-info/top_level.txt
Pop_Con-1.0.5.dist-info/RECORD
