Metadata-Version: 2.1
Name: Pop-Con
Version: 1.0.5
Summary: Visualization of genotype profiles on population genomics data for detection of abnormal genotypes pattern.
Home-page: https://github.com/YoannAnselmetti/Pop-Con
Author: Yoann Anselmetti
Author-email: yoann.anselmetti@umontpellier.fr
License: CeCILL-2.1
Platform: UNKNOWN
Classifier: Development Status :: 4 - Beta
Classifier: Environment :: Console
Classifier: Intended Audience :: Science/Research
Classifier: License :: OSI Approved :: CEA CNRS Inria Logiciel Libre License, version 2.1 (CeCILL-2.1)
Classifier: Natural Language :: English
Classifier: Operating System :: POSIX :: Linux
Classifier: Programming Language :: Python
Classifier: Topic :: Scientific/Engineering :: Bio-Informatics
Classifier: Topic :: Scientific/Engineering :: Visualization
Requires-Dist: matplotlib (==2.2.4)
Requires-Dist: numpy (==1.16.4)
Requires-Dist: cyvcf2 (==0.11.4)
